odoo8_addon_account_import_line_multicurrency_extension-8.0.1.1.0.99.dev11-py2.7-nspkg.pth
odoo8_addon_account_import_line_multicurrency_extension-8.0.1.1.0.99.dev11.dist-info/DESCRIPTION.rst
odoo8_addon_account_import_line_multicurrency_extension-8.0.1.1.0.99.dev11.dist-info/METADATA
odoo8_addon_account_import_line_multicurrency_extension-8.0.1.1.0.99.dev11.dist-info/RECORD
odoo8_addon_account_import_line_multicurrency_extension-8.0.1.1.0.99.dev11.dist-info/WHEEL
odoo8_addon_account_import_line_multicurrency_extension-8.0.1.1.0.99.dev11.dist-info/metadata.json
odoo8_addon_account_import_line_multicurrency_extension-8.0.1.1.0.99.dev11.dist-info/namespace_packages.txt
odoo8_addon_account_import_line_multicurrency_extension-8.0.1.1.0.99.dev11.dist-info/top_level.txt
odoo_addons/account_import_line_multicurrency_extension/README.rst
odoo_addons/account_import_line_multicurrency_extension/__init__.py
odoo_addons/account_import_line_multicurrency_extension/__openerp__.py
odoo_addons/account_import_line_multicurrency_extension/i18n/account_import_line_multicurrency_extension.pot
odoo_addons/account_import_line_multicurrency_extension/i18n/de.po
odoo_addons/account_import_line_multicurrency_extension/i18n/en_GB.po
odoo_addons/account_import_line_multicurrency_extension/i18n/es.po
odoo_addons/account_import_line_multicurrency_extension/i18n/fr.po
odoo_addons/account_import_line_multicurrency_extension/i18n/nl_NL.po
odoo_addons/account_import_line_multicurrency_extension/i18n/pt_BR.po
odoo_addons/account_import_line_multicurrency_extension/i18n/pt_PT.po
odoo_addons/account_import_line_multicurrency_extension/i18n/sl.po
odoo_addons/account_import_line_multicurrency_extension/models/__init__.py
odoo_addons/account_import_line_multicurrency_extension/models/account_statement_from_invoice.py
odoo_addons/account_import_line_multicurrency_extension/models/bank_statement.py
odoo_addons/account_import_line_multicurrency_extension/static/description/icon.png
odoo_addons/account_import_line_multicurrency_extension/view/account_statement_from_invoice_view.xml
odoo_addons/account_import_line_multicurrency_extension/view/bank_statement_view.xml
